edynamics/__init__.py
edynamics/data_sets/__init__.py
edynamics/data_sets/lorenz.py
edynamics/modelling_tools/__init__.py
edynamics/modelling_tools/embeddings/__init__.py
edynamics/modelling_tools/embeddings/embedding.py
edynamics/modelling_tools/estimators/__init__.py
edynamics/modelling_tools/estimators/dimensionality.py
edynamics/modelling_tools/estimators/nonlinearity.py
edynamics/modelling_tools/estimators/observers.py
edynamics/modelling_tools/kernels/__init__.py
edynamics/modelling_tools/kernels/constant.py
edynamics/modelling_tools/kernels/epanechnikov.py
edynamics/modelling_tools/kernels/exponential.py
edynamics/modelling_tools/kernels/kernel.py
edynamics/modelling_tools/kernels/tricubic.py
edynamics/modelling_tools/mappers/__init__.py
edynamics/modelling_tools/mappers/cross_mapping.py
edynamics/modelling_tools/norms/__init__.py
edynamics/modelling_tools/norms/minkowski.py
edynamics/modelling_tools/norms/norm.py
edynamics/modelling_tools/observers/__init__.py
edynamics/modelling_tools/observers/observer.py
edynamics/modelling_tools/observers/observers.py
edynamics/modelling_tools/projectors/__init__.py
edynamics/modelling_tools/projectors/k_nearest_neighbours.py
edynamics/modelling_tools/projectors/projector.py
edynamics/modelling_tools/projectors/weighted_least_squares.py
edynamics/utils/ProgressBar.py
edynamics/utils/ProgressBarActor.py
edynamics/utils/__init__.py
edynamics-0.3.14.dist-info/METADATA
edynamics-0.3.14.dist-info/WHEEL
edynamics-0.3.14.dist-info/top_level.txt
edynamics-0.3.14.dist-info/RECORD
